{
  "name": "oarc-for-bno",
  "version": "2.1.25",
  "factorio_version": "2.0",
  "title": "Oarc Multiplayer Spawn for Brave New Oarc",
  "author": "Oarcinae & JustGoFly",
  "contact": "Forums, Discussion Page, https://discord.gg/pYqyjHQhqB , Vinnie@JustGoFly.com",
  "homepage": "https://discord.gg/pYqyjHQhqB",
  "description": "[[Description is in locale file!]]",
  "dependencies": [
    "base >= 2.0.17",
    "? space-age",
    "(?) dangOreus",
    "(?) Milestones",
    "(?) space-exploration",
    "(?) alien-biomes",
    "(?) sonaxaton-research-queue",
    "(?) helmod",
    "(?) blueprint-sandboxes",
    "(?) factorissimo-2-notnotmelon",
    "(?) better-chat",
    "! rso-mod"
  ]
}
